scratchpad/__init__.py
scratchpad/composite_logger.py
scratchpad/console_logger.py
scratchpad/file_logger.py
scratchpad/fluent_logger.py
scratchpad/jandi_logger.py
scratchpad/line_logger.py
scratchpad/logger.py
scratchpad/logger_impl.py
scratchpad/logger_interface.py
scratchpad/memory_logger.py
scratchpad/null_logger.py
scratchpad/retry.py
scratchpad/scribe_logger.py
scratchpad/slack_logger.py
scratchpad/telegram_logger.py
scratchpad_py-0.0.7.dist-info/LICENSE
scratchpad_py-0.0.7.dist-info/METADATA
scratchpad_py-0.0.7.dist-info/WHEEL
scratchpad_py-0.0.7.dist-info/top_level.txt
scratchpad_py-0.0.7.dist-info/RECORD
