Metadata-Version: 2.1
Name: scratchpad-py
Version: 0.0.7
Summary: python logger libary
Home-page: https://github.com/chirichidi/scratch-pad-py
Author: chirichidi
Author-email: tolessnoise@gmail.com
Keywords: logger
Classifier: Programming Language :: Python :: 3.7
Classifier: License :: OSI Approved :: MIT License
Classifier: Operating System :: OS Independent
Requires-Python: >=3.7
License-File: LICENSE
Requires-Dist: requests>=2.0.0
Requires-Dist: thrift>=0.16.0
Requires-Dist: facebook-scribe>=2.0.post1
Requires-Dist: fluent-logger>=0.10.0
